pidili/__init__.py
pidili/buffers.py
pidili/colors.py
pidili/diff.py
pidili/pidili.py
pidili/render.py
pidili/utils.py
pidili/widgets.py
pidili-0.1.1.dist-info/METADATA
pidili-0.1.1.dist-info/WHEEL
pidili-0.1.1.dist-info/licenses/LICENSE.txt
pidili-0.1.1.dist-info/RECORD
