Metadata-Version: 2.4
Name: pidili
Version: 0.1.1
Summary: Declarative display library for smartscreens based on Pillow
Project-URL: homepage, https://github.com/hchargois/pidili
Author-email: Hugo Chargois <hugo.chargois@free.fr>
License-File: LICENSE.txt
Classifier: License :: OSI Approved :: MIT License
Classifier: Operating System :: OS Independent
Classifier: Programming Language :: Python :: 3
Requires-Python: >=3.12
Requires-Dist: numpy>=2.0.2
Requires-Dist: pillow>=11.0.0
